soliddriver_checks/__init__.py
soliddriver_checks/config.py
soliddriver_checks/version.py
soliddriver_checks/api/__init__.py
soliddriver_checks/api/analysis.py
soliddriver_checks/api/filter.py
soliddriver_checks/api/km.py
soliddriver_checks/api/kmp.py
soliddriver_checks/api/raw_data.py
soliddriver_checks/api/utils/__init__.py
soliddriver_checks/api/utils/cmd.py
soliddriver_checks/api/utils/scripts/check-links.sh
soliddriver_checks/cli/__init__.py
soliddriver_checks/cli/cli.py
soliddriver_checks/cli/km_report.py
soliddriver_checks/cli/kmp_report.py
soliddriver_checks/cli/terminal_logs.py
soliddriver_checks/cli/xlsx_utils.py
soliddriver_checks/config/soliddriver-checks.conf
soliddriver_checks/config/templates/km-report.html.jinja
soliddriver_checks/config/templates/kmp-report.html.jinja
soliddriver_checks/config/templates/templates.xlsx
soliddriver_checks/service/__init__.py
soliddriver_checks/service/service.py
soliddriver_checks-3.0.8.dist-info/LICENSE
soliddriver_checks-3.0.8.dist-info/METADATA
soliddriver_checks-3.0.8.dist-info/WHEEL
soliddriver_checks-3.0.8.dist-info/entry_points.txt
soliddriver_checks-3.0.8.dist-info/top_level.txt
soliddriver_checks-3.0.8.dist-info/RECORD
