Metadata-Version: 2.1
Name: soliddriver-checks
Version: 3.0.8
Summary: Check Kernel Module Package and Kernel Module information
Home-page: https://github.com/SUSE/soliddriver-checks
Author: Hui-Zhi Zhao
Author-email: hui.zhi.zhao@suse.com
Project-URL: Bug Tracker, https://github.com/SUSE/soliddriver-checks/issues
Classifier: Programming Language :: Python :: 3
Classifier: License :: OSI Approved :: GNU General Public License v2 (GPLv2)
Classifier: Operating System :: OS Independent
Requires-Python: >=3.7
License-File: LICENSE
Requires-Dist: bottle (>=0.12.23)
Requires-Dist: click (>=8.1.3)
Requires-Dist: dominate (>=2.7.0)
Requires-Dist: Jinja2 (>=3.1.2)
Requires-Dist: openpyxl (>=3.0.10)
Requires-Dist: pandas (>=1.5.2)
Requires-Dist: rich (>=12.6.0)
Requires-Dist: setuptools (>=65.4.1)
Requires-Dist: requests (>=2.28.1)
